diffxl/__init__.py
diffxl/diagnostic_generator.py
diffxl/diff_engine.py
diffxl/html_generator.py
diffxl/main.py
diffxl/smart_loader.py
diffxl/utils.py
diffxl-0.1.0.dist-info/METADATA
diffxl-0.1.0.dist-info/WHEEL
diffxl-0.1.0.dist-info/entry_points.txt
diffxl-0.1.0.dist-info/licenses/LICENSE
diffxl-0.1.0.dist-info/RECORD
