Metadata-Version: 2.4
Name: diffxl
Version: 0.1.0
Summary: A CLI tool for finding differences between Excel files based on a UID column.
Project-URL: Homepage, https://github.com/meerola/diffxl
Project-URL: Repository, https://github.com/meerola/diffxl
Project-URL: Issues, https://github.com/meerola/diffxl/issues
Author-email: Mikael Eerola <dev.meerola@gmail.com>
License-Expression: MIT
License-File: LICENSE
Keywords: cli,comparison,data-integrity,diff,excel
Classifier: Development Status :: 4 - Beta
Classifier: Intended Audience :: Developers
Classifier: Intended Audience :: Financial and Insurance Industry
Classifier: License :: OSI Approved :: MIT License
Classifier: Programming Language :: Python :: 3.13
Classifier: Topic :: Office/Business :: Financial :: Spreadsheet
Classifier: Topic :: Utilities
Requires-Python: >=3.13
Requires-Dist: jinja2
Requires-Dist: openpyxl
Requires-Dist: pandas
Requires-Dist: rich
Requires-Dist: xlrd
